dbpoolpy/__init__.py
dbpoolpy/constants.py
dbpoolpy/dbpool.py
dbpoolpy/table.py
dbpoolpy/utils.py
dbpoolpy/config/__init__.py
dbpoolpy/config/custom_settings.py
dbpoolpy/config/default_settings.py
dbpoolpy/config/functional.py
dbpoolpy/dbconnect/__init__.py
dbpoolpy/dbconnect/mysql.py
dbpoolpy/dbconnect/postgresql.py
dbpoolpy/dbconnect/simple.py
dbpoolpy/dbconnect/sqlite3.py
dbpoolpy/dbhelper/__init__.py
dbpoolpy/dbhelper/mysql.py
dbpoolpy/dbhelper/postgresql.py
dbpoolpy/dbhelper/sqlite3.py
dbpoolpy-0.6.11.dist-info/LICENSE
dbpoolpy-0.6.11.dist-info/METADATA
dbpoolpy-0.6.11.dist-info/WHEEL
dbpoolpy-0.6.11.dist-info/top_level.txt
dbpoolpy-0.6.11.dist-info/RECORD
