Metadata-Version: 2.1
Name: dbpoolpy
Version: 0.6.11
Summary: A simple Python library for easily connect to db 2.0.
Home-page: https://gitee.com/zsq_tee/dbpoolpy
Author: Shuiqing Zheng
Author-email: shuiqingzheng@126.com
License: MIT
Project-URL: Documentation, https://gitee.com/zsq_tee/dbpoolpy
Project-URL: Source, https://gitee.com/zsq_tee/dbpoolpy
Requires-Python: >=3.6
License-File: LICENSE
